boilerplates/__init__.py
boilerplates/cli.py
boilerplates/config.py
boilerplates/git_repo_tests.py
boilerplates/logging.py
boilerplates/packaging_tests.py
boilerplates/py.typed
boilerplates/sentry.py
boilerplates/setup.py
boilerplates/bundled_version_query/__init__.py
boilerplates/bundled_version_query/git_query.py
boilerplates/bundled_version_query/parser.py
boilerplates/bundled_version_query/patterns.py
boilerplates/bundled_version_query/py.typed
boilerplates/bundled_version_query/py_query.py
boilerplates/bundled_version_query/query.py
boilerplates/bundled_version_query/version.py
boilerplates-1.2.4.dist-info/licenses/LICENSE
boilerplates-1.2.4.dist-info/licenses/NOTICE
boilerplates-1.2.4.dist-info/METADATA
boilerplates-1.2.4.dist-info/WHEEL
boilerplates-1.2.4.dist-info/top_level.txt
boilerplates-1.2.4.dist-info/RECORD
