Metadata-Version: 2.4
Name: boilerplates
Version: 1.2.4
Summary: Various boilerplates used in almost all of my Python packages.
Home-page: https://github.com/mbdevpl/python-boilerplates
Download-URL: 
Author: Mateusz Bysiek, Stian Hanssen
Author-email: mateusz.bysiek@gmail.com
Maintainer: Mateusz Bysiek
Maintainer-email: mateusz.bysiek@gmail.com
License-Expression: Apache-2.0
Keywords: git,logging,packaging,releasing
Classifier: Development Status :: 5 - Production/Stable
Classifier: Intended Audience :: Developers
Classifier: Operating System :: MacOS
Classifier: Operating System :: Microsoft :: Windows
Classifier: Operating System :: POSIX :: Linux
Classifier: Programming Language :: Python :: 3.9
Classifier: Programming Language :: Python :: 3.10
Classifier: Programming Language :: Python :: 3.11
Classifier: Programming Language :: Python :: 3.12
Classifier: Programming Language :: Python :: 3.13
Classifier: Programming Language :: Python :: 3 :: Only
Classifier: Topic :: Software Development :: Version Control :: Git
Classifier: Topic :: System :: Archiving :: Packaging
Classifier: Topic :: System :: Installation/Setup
Classifier: Topic :: System :: Logging
Classifier: Topic :: System :: Software Distribution
Classifier: Topic :: Utilities
Classifier: Typing :: Typed
Requires-Python: >=3.9
License-File: LICENSE
License-File: NOTICE
Provides-Extra: setup
Requires-Dist: docutils~=0.20; extra == "setup"
Requires-Dist: Pygments~=2.14; extra == "setup"
Requires-Dist: setuptools>=77.0.3; extra == "setup"
Provides-Extra: packaging-tests
Requires-Dist: docutils~=0.20; extra == "packaging-tests"
Requires-Dist: Pygments~=2.14; extra == "packaging-tests"
Requires-Dist: setuptools>=77.0.3; extra == "packaging-tests"
Requires-Dist: build~=1.2; extra == "packaging-tests"
Requires-Dist: pip>=24.0; extra == "packaging-tests"
Requires-Dist: wheel>=0.43; extra == "packaging-tests"
Provides-Extra: config
Provides-Extra: logging
Requires-Dist: colorlog~=6.7; extra == "logging"
Provides-Extra: sentry
Requires-Dist: sentry-sdk[pure_eval]~=2.5; extra == "sentry"
Provides-Extra: cli
Requires-Dist: argcomplete~=3.1; extra == "cli"
Provides-Extra: git-repo-tests
Requires-Dist: GitPython~=3.1; extra == "git-repo-tests"
Dynamic: author
Dynamic: author-email
Dynamic: classifier
Dynamic: description
Dynamic: description-content-type
Dynamic: home-page
Dynamic: keywords
Dynamic: license-file
Dynamic: license-expression
Dynamic: maintainer
Dynamic: maintainer-email
Dynamic: provides-extra
Dynamic: requires-python
Dynamic: summary
